tensorhub/__init__.py
tensorhub_ai-1.0.dist-info/LICENSE
tensorhub_ai-1.0.dist-info/METADATA
tensorhub_ai-1.0.dist-info/WHEEL
tensorhub_ai-1.0.dist-info/top_level.txt
tensorhub_ai-1.0.dist-info/RECORD
